{
    "_links": {
        "self": {
            "href": "http:\/\/default\/sites\/default\/files\/inline-images\/desktopwallpapers.org_.ua-9186_0.jpg"
        },
        "type": {
            "href": "http:\/\/drupal.org\/rest\/type\/file\/file"
        },
        "http:\/\/drupal.org\/rest\/relation\/file\/file\/uid": [
            {
                "href": "http:\/\/default\/user\/1?_format=hal_json"
            }
        ]
    },
    "fid": [
        {
            "value": 5
        }
    ],
    "uuid": [
        {
            "value": "d1ffa7a4-24bc-4c6d-a310-f2c2c01297c2"
        }
    ],
    "langcode": [
        {
            "value": "en"
        }
    ],
    "_embedded": {
        "http:\/\/drupal.org\/rest\/relation\/file\/file\/uid": [
            {
                "_links": {
                    "self": {
                        "href": "http:\/\/default\/user\/1?_format=hal_json"
                    },
                    "type": {
                        "href": "http:\/\/drupal.org\/rest\/type\/user\/user"
                    }
                },
                "uuid": [
                    {
                        "value": "6b962f9b-bd5e-4f4c-8bd6-20af0da77e44"
                    }
                ]
            }
        ]
    },
    "filename": [
        {
            "value": "desktopwallpapers.org_.ua-9186.jpg"
        }
    ],
    "uri": [
        {
            "value": "public:\/\/inline-images\/desktopwallpapers.org_.ua-9186_0.jpg",
            "url": "\/sites\/default\/files\/inline-images\/desktopwallpapers.org_.ua-9186_0.jpg"
        }
    ],
    "filemime": [
        {
            "value": "image\/jpeg"
        }
    ],
    "filesize": [
        {
            "value": 3228147
        }
    ],
    "status": [
        {
            "value": true
        }
    ],
    "created": [
        {
            "value": "2018-10-10T08:39:11+00:00",
            "format": "Y-m-d\\TH:i:sP"
        }
    ],
    "changed": [
        {
            "value": "2018-10-10T08:43:15+00:00",
            "format": "Y-m-d\\TH:i:sP"
        }
    ]
}